README.md
setup.py
test/test.py
yaml_param_search/__init__.py
yaml_param_search/search.py
yaml_param_search.egg-info/PKG-INFO
yaml_param_search.egg-info/SOURCES.txt
yaml_param_search.egg-info/dependency_links.txt
yaml_param_search.egg-info/requires.txt
yaml_param_search.egg-info/top_level.txt